voss_taren/__init__.py
voss_taren/main.py
voss_taren-1.1.0.dist-info/METADATA
voss_taren-1.1.0.dist-info/WHEEL
voss_taren-1.1.0.dist-info/entry_points.txt
voss_taren-1.1.0.dist-info/top_level.txt
voss_taren-1.1.0.dist-info/RECORD
