Metadata-Version: 2.4
Name: voss-taren
Version: 1.1.0
Summary: Effet Matrix authentique en Python
Author: Votre Nom
Classifier: Programming Language :: Python :: 3
Classifier: Operating System :: OS Independent
Requires-Python: >=3.6
Dynamic: author
Dynamic: classifier
Dynamic: description
Dynamic: description-content-type
Dynamic: requires-python
Dynamic: summary
